MANIFEST.in
README.txt
setup.py
collective/__init__.py
collective.z3cform.datepicker.egg-info/PKG-INFO
collective.z3cform.datepicker.egg-info/SOURCES.txt
collective.z3cform.datepicker.egg-info/dependency_links.txt
collective.z3cform.datepicker.egg-info/entry_points.txt
collective.z3cform.datepicker.egg-info/namespace_packages.txt
collective.z3cform.datepicker.egg-info/not-zip-safe
collective.z3cform.datepicker.egg-info/requires.txt
collective.z3cform.datepicker.egg-info/top_level.txt
collective/z3cform/__init__.py
collective/z3cform/datepicker/__init__.py
collective/z3cform/datepicker/configure.zcml
collective/z3cform/datepicker/datepicker_input.pt
collective/z3cform/datepicker/datetimepicker_input.pt
collective/z3cform/datepicker/interfaces.py
collective/z3cform/datepicker/test.zcml
collective/z3cform/datepicker/tests.py
collective/z3cform/datepicker/version.txt
collective/z3cform/datepicker/widget.py
docs/HISTORY.txt
docs/INSTALL.txt
docs/LICENSE.GPL
docs/LICENSE.txt