Metadata-Version: 1.0
Name: collective.z3cform.datepicker
Version: 0.1rc7
Summary: calendar widget for z3c.form
Home-page: http://github.com/garbas/collective.z3cform.datepicker
Author: Rok Garbas
Author-email: rok.garbas@gmail.com
License: GPL
Keywords: zope plone z3c.form plone.z3cform collective datepicker calendar jquery
Platform: UNKNOWN
Classifier: Framework :: Plone
Classifier: Programming Language :: Python
Classifier: Topic :: Software Development :: Libraries :: Python Modules
